pymicrostructure/__init__.py
pymicrostructure/markets/__init__.py
pymicrostructure/markets/base.py
pymicrostructure/markets/continuous.py
pymicrostructure/metrics/__init__.py
pymicrostructure/metrics/market.py
pymicrostructure/metrics/trader.py
pymicrostructure/orders/__init__.py
pymicrostructure/orders/base.py
pymicrostructure/orders/limit.py
pymicrostructure/orders/market.py
pymicrostructure/traders/__init__.py
pymicrostructure/traders/base.py
pymicrostructure/traders/ensemble.py
pymicrostructure/traders/informed.py
pymicrostructure/traders/market_maker.py
pymicrostructure/traders/noise.py
pymicrostructure/traders/strategy.py
pymicrostructure/utils/__init__.py
pymicrostructure/utils/utils.py
pymicrostructure/visualization/__init__.py
pymicrostructure/visualization/summary.py
pymicrostructure-0.0.2.dist-info/LICENSE.md
pymicrostructure-0.0.2.dist-info/METADATA
pymicrostructure-0.0.2.dist-info/WHEEL
pymicrostructure-0.0.2.dist-info/top_level.txt
pymicrostructure-0.0.2.dist-info/RECORD
