Metadata-Version: 2.1
Name: pymicrostructure
Version: 0.0.2
Summary: Simulate financial markets
Author-email: Bartosz Bieganowski <bartosz.bieganowski.office@gmail.com>
License: Copyright (c) 2024, ROBUST GAMMA BARTOSZ BIEGANOWSKI
Project-URL: Homepage, https://github.com/BBieganowski/pymicrostructure
Keywords: finance,quant,trading
Classifier: License :: OSI Approved :: MIT License
Classifier: Programming Language :: Python
Classifier: Programming Language :: Python :: 3
Requires-Python: >=3.11
License-File: LICENSE.md
Requires-Dist: feedparser >=5.2.0
Requires-Dist: html2text
Requires-Dist: numpy >=2.0.0
Requires-Dist: pandas >=2.0.0
Requires-Dist: matplotlib >=3.9.0
Requires-Dist: tqdm >=4.0.0
Requires-Dist: dill >=0.3.4
Requires-Dist: scipy >=1.7.0
Requires-Dist: statsmodels >=0.13.0
Requires-Dist: seaborn >=0.11.2
Requires-Dist: tomli ; python_version >= "3.11"
Provides-Extra: dev
Requires-Dist: black ; extra == 'dev'
Requires-Dist: bumpver ; extra == 'dev'
Requires-Dist: isort ; extra == 'dev'
Requires-Dist: pip-tools ; extra == 'dev'
Requires-Dist: pytest ; extra == 'dev'
